<PAMDataset>
  <Metadata domain="IMAGE_STRUCTURE">
    <MDI key="SOURCE_COLOR_SPACE">YCbCr</MDI>
    <MDI key="INTERLEAVE">PIXEL</MDI>
    <MDI key="COMPRESSION">JPEG</MDI>
  </Metadata>
  <PAMRasterBand band="1">
    <Metadata>
      <MDI key="STATISTICS_APPROXIMATE">YES</MDI>
      <MDI key="STATISTICS_MINIMUM">68</MDI>
      <MDI key="STATISTICS_MAXIMUM">255</MDI>
      <MDI key="STATISTICS_MEAN">237.22116499736</MDI>
      <MDI key="STATISTICS_STDDEV">21.057342077383</MDI>
      <MDI key="STATISTICS_VALID_PERCENT">100</MDI>
    </Metadata>
    <Metadata domain="IMAGE_STRUCTURE">
      <MDI key="COMPRESSION">JPEG</MDI>
    </Metadata>
  </PAMRasterBand>
  <PAMRasterBand band="2">
    <Metadata>
      <MDI key="STATISTICS_APPROXIMATE">YES</MDI>
      <MDI key="STATISTICS_MINIMUM">61</MDI>
      <MDI key="STATISTICS_MAXIMUM">253</MDI>
      <MDI key="STATISTICS_MEAN">222.59938060095</MDI>
      <MDI key="STATISTICS_STDDEV">20.506485008335</MDI>
      <MDI key="STATISTICS_VALID_PERCENT">100</MDI>
    </Metadata>
    <Metadata domain="IMAGE_STRUCTURE">
      <MDI key="COMPRESSION">JPEG</MDI>
    </Metadata>
  </PAMRasterBand>
  <PAMRasterBand band="3">
    <Metadata>
      <MDI key="STATISTICS_APPROXIMATE">YES</MDI>
      <MDI key="STATISTICS_MINIMUM">53</MDI>
      <MDI key="STATISTICS_MAXIMUM">224</MDI>
      <MDI key="STATISTICS_MEAN">195.60454665261</MDI>
      <MDI key="STATISTICS_STDDEV">19.049056689829</MDI>
      <MDI key="STATISTICS_VALID_PERCENT">100</MDI>
    </Metadata>
    <Metadata domain="IMAGE_STRUCTURE">
      <MDI key="COMPRESSION">JPEG</MDI>
    </Metadata>
  </PAMRasterBand>
</PAMDataset>
